khachkhach/__init__.py
khachkhach/data_processor.py
khachkhach/detection_engine.py
khachkhach/utils.py
khachkhach/video_processor.py
khachkhach/__pycache__/__init__.cpython-312.pyc
khachkhach/__pycache__/data_processor.cpython-312.pyc
khachkhach/__pycache__/detection_engine.cpython-312.pyc
khachkhach/__pycache__/utils.cpython-312.pyc
khachkhach/__pycache__/video_processor.cpython-312.pyc
khachkhach-2.0.3.dist-info/licenses/LICENSE
khachkhach-2.0.3.dist-info/METADATA
khachkhach-2.0.3.dist-info/WHEEL
khachkhach-2.0.3.dist-info/top_level.txt
khachkhach-2.0.3.dist-info/RECORD
