Metadata-Version: 2.4
Name: KhachKhach
Version: 2.0.3
Summary: A package for processing video frames, annotating keypoints, and more.
Home-page: https://github.com/pratapsdev11/Khach_Khach
Author: pratapdevs11
Author-email: divyapratap360@gmail.com
License: MIT
Project-URL: Source, https://github.com/pratapsdev11/Khach_Khach
Project-URL: Tracker, https://github.com/pratapsdev11/Khach_Khach/issues
Classifier: Programming Language :: Python :: 3
Classifier: License :: OSI Approved :: MIT License
Classifier: Operating System :: OS Independent
Requires-Python: >=3.6
License-File: LICENSE
Requires-Dist: opencv-python>=4.5.0
Requires-Dist: numpy>=1.20.0
Requires-Dist: pillow>=8.0.0
Requires-Dist: ultralytics>=8.0.0
Requires-Dist: pathlib2>=2.3.0
Dynamic: author
Dynamic: author-email
Dynamic: classifier
Dynamic: description
Dynamic: description-content-type
Dynamic: home-page
Dynamic: license
Dynamic: license-file
Dynamic: project-url
Dynamic: requires-dist
Dynamic: requires-python
Dynamic: summary
